signature_altering/__init__.py
signature_altering-0.0.2.dist-info/DESCRIPTION.rst
signature_altering-0.0.2.dist-info/METADATA
signature_altering-0.0.2.dist-info/RECORD
signature_altering-0.0.2.dist-info/WHEEL
signature_altering-0.0.2.dist-info/metadata.json
signature_altering-0.0.2.dist-info/top_level.txt
tests/__init__.py
tests/test_signature_altering.py
