Metadata-Version: 2.0
Name: signature-altering
Version: 0.0.2
Summary: Create decorators that alter the signatures of decorated functions in predictable ways
Home-page: https://github.com/gvx/signature-altering
Author: Robin Wellner
Author-email: rwellner0@gmail.com
License: MIT
